freeotp_export/__init__.py
freeotp_export/__main__.py
freeotp_export-0.1.1.dist-info/licenses/LICENSE.txt
freeotp_export-0.1.1.dist-info/METADATA
freeotp_export-0.1.1.dist-info/WHEEL
freeotp_export-0.1.1.dist-info/entry_points.txt
freeotp_export-0.1.1.dist-info/top_level.txt
freeotp_export-0.1.1.dist-info/RECORD
