Metadata-Version: 2.4
Name: freeotp-export
Version: 0.1.1
Summary: Parse a FreeOTP xml file and present QR codes or strings for import elsewhere
Author-email: Trevor Bergeron <mal@sec.gd>
Classifier: Development Status :: 4 - Beta
Classifier: License :: OSI Approved :: European Union Public Licence 1.2 (EUPL 1.2)
Classifier: Operating System :: OS Independent
Requires-Python: ~=3.9
License-File: LICENSE.txt
Requires-Dist: qrcode~=7.3.1
Dynamic: license-file
